dynamo_dao/__init__.py
dynamo_dao/dao.py
dynamo_dao/dynamo.py
dynamo_dao/py.typed
dynamo_dao-0.0.7.dist-info/LICENSE
dynamo_dao-0.0.7.dist-info/METADATA
dynamo_dao-0.0.7.dist-info/WHEEL
dynamo_dao-0.0.7.dist-info/top_level.txt
dynamo_dao-0.0.7.dist-info/RECORD
