Metadata-Version: 2.1
Name: dynamo-dao
Version: 0.0.7
Summary: Dynamo Dao
Home-page: https://github.com/qsweber/dynamo-dao
Author: Quinn Weber
Author-email: quinn@quinnweber.com
Maintainer: Quinn Weber
Maintainer-email: quinn@quinnweber.com
License: MIT
Platform: UNKNOWN
Classifier: Programming Language :: Python :: 3
Classifier: License :: OSI Approved :: MIT License
Classifier: Operating System :: OS Independent
Requires-Dist: Boto3
